{
  "id": 2000000339,
  "name": "Aura Armor",
  "is_illegal": false,
  "is_custom": true,
  "text": "Activate only when an opponent's monster declares a direct attack while your Life Points are 2000 or less. Negate the attack, and Special Summon 1 \"Player Token\" (Warrior-Type/EARTH/Level 4/ATK ?/DEF ?). When that \"Player Token\" is Special Summoned, halve your Life Points. The ATK and DEF of \"Player Token\" are equal to your Life Points.",
  "images": [
    "https://raw.githubusercontent.com/JustBryant/KingdomsImages/main/KP4/aura_armor.jpg"
  ],
  "type": "Trap",
  "trap_type": "Normal"
}
