{
  "id": 2000000316,
  "name": "Red-Eyes Phoenix",
  "is_illegal": false,
  "is_custom": true,
  "text": "This card's name becomes \"Red-Eyes Black Dragon\" on the field or in the GY. If a \"Red-Eyes\" Dragon monster is sent to the GY while this card is in the GY: Special Summon this card in face-up Defense Position but its ATK becomes 0. If you do, monsters your opponent currently controls lose 400 ATK until the end of the turn. You can only use the effect of \"Red-Eyes Phoenix\" once per turn.",
  "images": [
    "https://raw.githubusercontent.com/JustBryant/KingdomsImages/main/KP4/red-eyes_phoenix.jpg"
  ],
  "type": "Monster",
  "attribute": "DARK",
  "atk": 1800,
  "species": "Dragon",
  "monster_type": "Effect",
  "is_pendulum": false,
  "ability": "",
  "has_effect": true,
  "def": 2400,
  "level": 7,
  "is_tuner": false
}
